spirol-1.0.0.dist-info/RECORD
spirol-1.0.0.dist-info/METADATA
spirol-1.0.0.dist-info/WHEEL
spirol-1.0.0.dist-info/top_level.txt
spirol-1.0.0.dist-info/DESCRIPTION.rst
spirol-1.0.0.dist-info/metadata.json
spirol/impl_factory.py
spirol/__init__.py
spirol/core.py
spirol/utils.py
spirol/errors.py
spirol/impls/spirol_array_iter.py
spirol/impls/__init__.py
