Metadata-Version: 2.0
Name: spirol
Version: 1.0.0
Summary: A pure-python non-repeating outside-in spiral iterator-generator for 2D arrays
Home-page: https://bitbucket.org/sys-git/spirol
Author: Francis Horsman
Author-email: francis.horsman@gmail.com
License: GNU General Public License
Keywords: algorithms
Platform: any
Classifier: Development Status :: 5 - Production/Stable
Classifier: Intended Audience :: Developers
Classifier: License :: OSI Approved :: GNU General Public License v3 (GPLv3)
Classifier: Operating System :: OS Independent
Classifier: Programming Language :: Python
Classifier: Topic :: Software Development :: Libraries :: Python Modules
Requires-Dist: futures (>=2.2.0)
Requires-Dist: nose (>=1.3.1)
Requires-Dist: coverage (>=3.7.1)
Requires-Dist: shifty (==0.0.3)
